fylax/__init__.py
fylax/gui.py
fylax/main.py
fylax-1.0.1.dist-info/licenses/LICENSE
fylax-1.0.1.dist-info/METADATA
fylax-1.0.1.dist-info/WHEEL
fylax-1.0.1.dist-info/entry_points.txt
fylax-1.0.1.dist-info/top_level.txt
fylax-1.0.1.dist-info/RECORD
