Metadata-Version: 2.4
Name: fylax
Version: 1.0.1
Summary: A smart file organization utility that automatically sorts files into structured folders based on customizable rules
Author-email: John Tocci <john@johntocci.com>
License: MIT
Project-URL: Homepage, https://github.com/JohnTocci/Fylax
Project-URL: Documentation, https://github.com/JohnTocci/Fylax#readme
Project-URL: Repository, https://github.com/JohnTocci/Fylax
Project-URL: Bug Tracker, https://github.com/JohnTocci/Fylax/issues
Project-URL: Changelog, https://github.com/JohnTocci/Fylax/blob/main/CHANGELOG.md
Project-URL: Discussions, https://github.com/JohnTocci/Fylax/discussions
Keywords: file-organization,automation,file-management,gui,desktop-app
Classifier: Development Status :: 5 - Production/Stable
Classifier: Intended Audience :: End Users/Desktop
Classifier: Topic :: Desktop Environment :: File Managers
Classifier: Topic :: System :: Filesystems
Classifier: Topic :: Utilities
Classifier: License :: OSI Approved :: MIT License
Classifier: Programming Language :: Python :: 3
Classifier: Programming Language :: Python :: 3.8
Classifier: Programming Language :: Python :: 3.9
Classifier: Programming Language :: Python :: 3.10
Classifier: Programming Language :: Python :: 3.11
Classifier: Programming Language :: Python :: 3.12
Classifier: Operating System :: OS Independent
Classifier: Operating System :: Microsoft :: Windows
Classifier: Operating System :: POSIX :: Linux
Classifier: Operating System :: MacOS
Classifier: Environment :: X11 Applications
Classifier: Environment :: Win32 (MS Windows)
Classifier: Environment :: MacOS X
Requires-Python: >=3.8
License-File: LICENSE
Requires-Dist: customtkinter>=5.2.2
Provides-Extra: dev
Requires-Dist: black>=23.0.0; extra == "dev"
Requires-Dist: isort>=5.12.0; extra == "dev"
Requires-Dist: flake8>=6.0.0; extra == "dev"
Requires-Dist: mypy>=1.0.0; extra == "dev"
Requires-Dist: pytest>=7.0.0; extra == "dev"
Requires-Dist: pytest-cov>=4.0.0; extra == "dev"
Requires-Dist: pyinstaller>=5.0.0; extra == "dev"
Provides-Extra: build
Requires-Dist: pyinstaller>=5.0.0; extra == "build"
Requires-Dist: setuptools>=61.0; extra == "build"
Requires-Dist: wheel; extra == "build"
Requires-Dist: twine; extra == "build"
Dynamic: license-file
